[
  {
    "State": "01",
    "median_salary_male": 2532.0,
    "median_salary_ot_male": 2564.0,
    "median_salary_female": 2200.0,
    "median_salary_ot_female": 2231.0,
    "median_salary_full": 2429.0,
    "median_salary_ot_full": 2473.5,
    "salary_gender_gap": 332.0,
    "salary_ot_gender_gap": 333.0,
    "state_name": "Johor"
  },
  {
    "State": "02",
    "median_salary_male": 1725.0,
    "median_salary_ot_male": 1805.0,
    "median_salary_female": 1554.0,
    "median_salary_ot_female": 1639.0,
    "median_salary_full": 1698.0,
    "median_salary_ot_full": 1748.0,
    "salary_gender_gap": 171.0,
    "salary_ot_gender_gap": 166.0,
    "state_name": "Kedah"
  },
  {
    "State": "03",
    "median_salary_male": 1650.0,
    "median_salary_ot_male": 1650.0,
    "median_salary_female": 1900.0,
    "median_salary_ot_female": 1900.0,
    "median_salary_full": 1650.0,
    "median_salary_ot_full": 1650.0,
    "salary_gender_gap": -250.0,
    "salary_ot_gender_gap": -250.0,
    "state_name": "Kelantan"
  },
  {
    "State": "04",
    "median_salary_male": 2332.0,
    "median_salary_ot_male": 2489.0,
    "median_salary_female": 1953.5,
    "median_salary_ot_female": 2160.5,
    "median_salary_full": 2209.0,
    "median_salary_ot_full": 2295.0,
    "salary_gender_gap": 378.5,
    "salary_ot_gender_gap": 328.5,
    "state_name": "Melaka"
  },
  {
    "State": "05",
    "median_salary_male": 2496.0,
    "median_salary_ot_male": 2564.0,
    "median_salary_female": 2261.0,
    "median_salary_ot_female": 2300.0,
    "median_salary_full": 2387.0,
    "median_salary_ot_full": 2500.0,
    "salary_gender_gap": 235.0,
    "salary_ot_gender_gap": 264.0,
    "state_name": "Negeri Sembilan"
  },
  {
    "State": "06",
    "median_salary_male": 2247.0,
    "median_salary_ot_male": 2300.0,
    "median_salary_female": 2000.0,
    "median_salary_ot_female": 2081.0,
    "median_salary_full": 2205.5,
    "median_salary_ot_full": 2261.0,
    "salary_gender_gap": 247.0,
    "salary_ot_gender_gap": 219.0,
    "state_name": "Pahang"
  },
  {
    "State": "07",
    "median_salary_male": 2346.0,
    "median_salary_ot_male": 2428.5,
    "median_salary_female": 2070.0,
    "median_salary_ot_female": 2133.0,
    "median_salary_full": 2261.0,
    "median_salary_ot_full": 2300.0,
    "salary_gender_gap": 276.0,
    "salary_ot_gender_gap": 295.5,
    "state_name": "Pulau Pinang"
  },
  {
    "State": "08",
    "median_salary_male": 1900.0,
    "median_salary_ot_male": 1995.0,
    "median_salary_female": 1670.0,
    "median_salary_ot_female": 1710.0,
    "median_salary_full": 1800.0,
    "median_salary_ot_full": 1840.0,
    "salary_gender_gap": 230.0,
    "salary_ot_gender_gap": 285.0,
    "state_name": "Perak"
  },
  {
    "State": "09",
    "median_salary_male": 2070.0,
    "median_salary_ot_male": 2070.0,
    "median_salary_female": 1600.0,
    "median_salary_ot_female": 1600.0,
    "median_salary_full": 1800.0,
    "median_salary_ot_full": 1905.0,
    "salary_gender_gap": 470.0,
    "salary_ot_gender_gap": 470.0,
    "state_name": "Perlis"
  },
  {
    "State": "10",
    "median_salary_male": 2956.0,
    "median_salary_ot_male": 2983.0,
    "median_salary_female": 2788.0,
    "median_salary_ot_female": 2788.0,
    "median_salary_full": 2875.0,
    "median_salary_ot_full": 2875.0,
    "salary_gender_gap": 168.0,
    "salary_ot_gender_gap": 195.0,
    "state_name": "Selangor"
  },
  {
    "State": "11",
    "median_salary_male": 1911.0,
    "median_salary_ot_male": 1911.0,
    "median_salary_female": 1463.0,
    "median_salary_ot_female": 1493.0,
    "median_salary_full": 1911.0,
    "median_salary_ot_full": 1911.0,
    "salary_gender_gap": 448.0,
    "salary_ot_gender_gap": 418.0,
    "state_name": "Terengganu"
  },
  {
    "State": "12",
    "median_salary_male": 1995.0,
    "median_salary_ot_male": 2015.0,
    "median_salary_female": 2070.0,
    "median_salary_ot_female": 2070.0,
    "median_salary_full": 2031.5,
    "median_salary_ot_full": 2070.0,
    "salary_gender_gap": -75.0,
    "salary_ot_gender_gap": -55.0,
    "state_name": "Sabah"
  },
  {
    "State": "13",
    "median_salary_male": 1800.0,
    "median_salary_ot_male": 1840.0,
    "median_salary_female": 2070.0,
    "median_salary_ot_female": 2070.0,
    "median_salary_full": 1840.0,
    "median_salary_ot_full": 1977.0,
    "salary_gender_gap": -270.0,
    "salary_ot_gender_gap": -230.0,
    "state_name": "Sarawak"
  },
  {
    "State": "14",
    "median_salary_male": 3096.0,
    "median_salary_ot_male": 3096.0,
    "median_salary_female": 3044.0,
    "median_salary_ot_female": 3050.0,
    "median_salary_full": 3096.0,
    "median_salary_ot_full": 3096.0,
    "salary_gender_gap": 52.0,
    "salary_ot_gender_gap": 46.0,
    "state_name": "W.P. Kuala Lumpur"
  },
  {
    "State": "15",
    "median_salary_male": 2645.0,
    "median_salary_ot_male": 2741.0,
    "median_salary_female": 1941.5,
    "median_salary_ot_female": 1941.5,
    "median_salary_full": 2515.0,
    "median_salary_ot_full": 2613.5,
    "salary_gender_gap": 703.5,
    "salary_ot_gender_gap": 799.5,
    "state_name": "W.P. Labuan"
  },
  {
    "State": "16",
    "median_salary_male": 4106.0,
    "median_salary_ot_male": 4106.0,
    "median_salary_female": 3710.0,
    "median_salary_ot_female": 3710.0,
    "median_salary_full": 4000.0,
    "median_salary_ot_full": 4000.0,
    "salary_gender_gap": 396.0,
    "salary_ot_gender_gap": 396.0,
    "state_name": "W.P. Putrajaya"
  }
]
